ants_platform/__init__.py
ants_platform/_client/attributes.py
ants_platform/_client/client.py
ants_platform/_client/constants.py
ants_platform/_client/datasets.py
ants_platform/_client/environment_variables.py
ants_platform/_client/get_client.py
ants_platform/_client/observe.py
ants_platform/_client/resource_manager.py
ants_platform/_client/span.py
ants_platform/_client/span_processor.py
ants_platform/_client/utils.py
ants_platform/_task_manager/media_manager.py
ants_platform/_task_manager/media_upload_consumer.py
ants_platform/_task_manager/media_upload_queue.py
ants_platform/_task_manager/score_ingestion_consumer.py
ants_platform/_utils/__init__.py
ants_platform/_utils/environment.py
ants_platform/_utils/error_logging.py
ants_platform/_utils/parse_error.py
ants_platform/_utils/prompt_cache.py
ants_platform/_utils/request.py
ants_platform/_utils/serializer.py
ants_platform/api/__init__.py
ants_platform/api/client.py
ants_platform/api/core/__init__.py
ants_platform/api/core/api_error.py
ants_platform/api/core/client_wrapper.py
ants_platform/api/core/datetime_utils.py
ants_platform/api/core/file.py
ants_platform/api/core/http_client.py
ants_platform/api/core/jsonable_encoder.py
ants_platform/api/core/pydantic_utilities.py
ants_platform/api/core/query_encoder.py
ants_platform/api/core/remove_none_from_dict.py
ants_platform/api/core/request_options.py
ants_platform/api/README.md
ants_platform/api/reference.md
ants_platform/api/resources/__init__.py
ants_platform/api/resources/annotation_queues/__init__.py
ants_platform/api/resources/annotation_queues/client.py
ants_platform/api/resources/annotation_queues/types/__init__.py
ants_platform/api/resources/annotation_queues/types/annotation_queue.py
ants_platform/api/resources/annotation_queues/types/annotation_queue_assignment_request.py
ants_platform/api/resources/annotation_queues/types/annotation_queue_item.py
ants_platform/api/resources/annotation_queues/types/annotation_queue_object_type.py
ants_platform-3.3.8.dist-info/entry_points.txt
ants_platform-3.3.8.dist-info/LICENSE
ants_platform-3.3.8.dist-info/METADATA
ants_platform-3.3.8.dist-info/WHEEL
ants_platform-3.3.8.dist-info/RECORD
